mls.py
mls-1.2.2.dist-info/WHEEL
mls-1.2.2.dist-info/top_level.txt
mls-1.2.2.dist-info/metadata.json
mls-1.2.2.dist-info/RECORD
mls-1.2.2.dist-info/DESCRIPTION.rst
mls-1.2.2.dist-info/METADATA
